realfakepg/__init__.py
realfakepg/pytest.py
realfakepg-0.0.0.dist-info/LICENSE.md
realfakepg-0.0.0.dist-info/METADATA
realfakepg-0.0.0.dist-info/WHEEL
realfakepg-0.0.0.dist-info/top_level.txt
realfakepg-0.0.0.dist-info/RECORD
